MANIFEST.in
README.rst
setup.py
auslfe/__init__.py
auslfe.portlet.multimedia.egg-info/PKG-INFO
auslfe.portlet.multimedia.egg-info/SOURCES.txt
auslfe.portlet.multimedia.egg-info/dependency_links.txt
auslfe.portlet.multimedia.egg-info/entry_points.txt
auslfe.portlet.multimedia.egg-info/namespace_packages.txt
auslfe.portlet.multimedia.egg-info/not-zip-safe
auslfe.portlet.multimedia.egg-info/requires.txt
auslfe.portlet.multimedia.egg-info/top_level.txt
auslfe/portlet/__init__.py
auslfe/portlet/multimedia/__init__.py
auslfe/portlet/multimedia/auslfeportletmultimedia.pt
auslfe/portlet/multimedia/auslfeportletmultimedia.py
auslfe/portlet/multimedia/configure.zcml
auslfe/portlet/multimedia/i18n.sh
auslfe/portlet/multimedia/upgrades.py
auslfe/portlet/multimedia/upgrades.zcml
auslfe/portlet/multimedia/Extensions/install.py
auslfe/portlet/multimedia/browser/__init__.py
auslfe/portlet/multimedia/browser/auslfe-accessible_css.js
auslfe/portlet/multimedia/browser/auslfe-multimediaportlet.css
auslfe/portlet/multimedia/browser/auslfe-multimediaportlet.js
auslfe/portlet/multimedia/browser/configure.zcml
auslfe/portlet/multimedia/browser/query_images.py
auslfe/portlet/multimedia/locales/auslfe.portlet.multimedia-manual.pot
auslfe/portlet/multimedia/locales/auslfe.portlet.multimedia.pot
auslfe/portlet/multimedia/locales/it/LC_MESSAGES/auslfe.portlet.multimedia.mo
auslfe/portlet/multimedia/locales/it/LC_MESSAGES/auslfe.portlet.multimedia.po
auslfe/portlet/multimedia/profiles/default/cssregistry.xml
auslfe/portlet/multimedia/profiles/default/jsregistry.xml
auslfe/portlet/multimedia/profiles/default/metadata.xml
auslfe/portlet/multimedia/profiles/default/portlets.xml
auslfe/portlet/multimedia/profiles/migrate_to_1000/jsregistry.xml
auslfe/portlet/multimedia/profiles/uninstall/cssregistry.xml
auslfe/portlet/multimedia/profiles/uninstall/jsregistry.xml
auslfe/portlet/multimedia/tests/__init__.py
auslfe/portlet/multimedia/tests/base.py
auslfe/portlet/multimedia/tests/test_portlet.py
docs/HISTORY.txt
docs/INSTALL.txt
docs/LICENSE.GPL
docs/LICENSE.txt