Metadata-Version: 1.0
Name: auslfe.portlet.multimedia
Version: 1.0.1
Summary: A simple Plone multimedia Portlet with an eye to accessibility
Home-page: http://plone.org/products/auslfe.portlet.multimedia
Author: RedTurtle Technology
Author-email: sviluppoplone@redturte.it
License: GPL
Keywords: plone jquery plonegov portlet multimedia image
Platform: UNKNOWN
Classifier: Framework :: Plone
Classifier: Framework :: Plone :: 4.0
Classifier: Framework :: Plone :: 4.2
Classifier: Framework :: Plone :: 4.3
Classifier: Programming Language :: Python
Classifier: Programming Language :: JavaScript
Classifier: Development Status :: 5 - Production/Stable
